duplicate_images/__init__.py
duplicate_images/common.py
duplicate_images/duplicate.py
duplicate_images/function_types.py
duplicate_images/hash_scanner/__init__.py
duplicate_images/hash_scanner/image_hash_scanner.py
duplicate_images/hash_store.py
duplicate_images/image_pair_finder.py
duplicate_images/log.py
duplicate_images/methods.py
duplicate_images/pair_finder_options.py
duplicate_images/parse_commandline.py
duplicate_images/progress_bar_manager.py
duplicate_images-0.11.10.dist-info/METADATA
duplicate_images-0.11.10.dist-info/WHEEL
duplicate_images-0.11.10.dist-info/entry_points.txt
duplicate_images-0.11.10.dist-info/licenses/LICENSE
duplicate_images-0.11.10.dist-info/RECORD
