Metadata-Version: 2.4
Name: duplicate_images
Version: 0.11.10
Summary: Finds equal or similar images in a directory containing (many) image files
License-File: LICENSE
Author: Lene Preuss
Author-email: lene.preuss@gmail.com
Requires-Python: >=3.12
Classifier: Development Status :: 4 - Beta
Classifier: Environment :: Console
Classifier: Programming Language :: Python :: 3
Classifier: Programming Language :: Python :: 3.12
Classifier: Programming Language :: Python :: 3.13
Classifier: Programming Language :: Python :: 3.14
Classifier: Topic :: Multimedia :: Graphics
Classifier: Topic :: Utilities
Requires-Dist: Wand (>=0.6)
Requires-Dist: coloredlogs (>=15.0)
Requires-Dist: filetype (>=1.2)
Requires-Dist: imagehash (>=4.3)
Requires-Dist: numpy (>=2.0)
Requires-Dist: pillow (>=11.0)
Requires-Dist: pillow-heif (>=0.21)
Requires-Dist: setuptools (>=75.6)
Requires-Dist: six (>=1.17)
Requires-Dist: tqdm (>=4.67)
Project-URL: Homepage, https://github.com/lene/DuplicateImages
Project-URL: Repository, https://github.com/lene/DuplicateImages.git
